{
  "project_info": {
    "project_number": "726205715451",
    "project_id": "unipdapp",
    "storage_bucket": "unipdapp.appspot.com"
  },
  "client": [
    {
      "client_info": {
        "mobilesdk_app_id": "1:726205715451:android:f8f3c0efc91724f96f715e",
        "android_client_info": {
          "package_name": "com.example.loginfede"
        }
      },
      "oauth_client": [
        {
          "client_id": "726205715451-snilc0to1jn8meg0gd98flfats8v4c4k.apps.googleusercontent.com",
          "client_type": 3
        }
      ],
      "api_key": [
        {
          "current_key": "AIzaSyDKZT1hRdpCJkWRxJmDyo5kEfNAOZ42NVY"
        }
      ],
      "services": {
        "appinvite_service": {
          "other_platform_oauth_client": [
            {
              "client_id": "726205715451-snilc0to1jn8meg0gd98flfats8v4c4k.apps.googleusercontent.com",
              "client_type": 3
            }
          ]
        }
      }
    }
  ],
  "configuration_version": "1"
}